{"version":1,"addons":{"firefox-compact-dark@mozilla.org":{"id":"firefox-compact-dark@mozilla.org","guid":"{a8accd21-8ecc-4c5e-9a19-274edbcfbb3c}","enabled":true,"installed":true,"modified":1772635462769,"type":"theme","scope":4,"foreignInstall":false,"isSyncable":false},"default-theme@mozilla.org":{"id":"default-theme@mozilla.org","guid":"{9f629ef4-2426-4ca0-96be-9559118a9c77}","enabled":false,"installed":true,"modified":1772635462792,"type":"theme","scope":4,"foreignInstall":false,"isSyncable":false},"data-leak-blocker@mozilla.com":{"id":"data-leak-blocker@mozilla.com","guid":"{9e09b930-58a9-4b77-b6db-789be3196c90}","enabled":true,"installed":true,"modified":1772635467925,"type":"extension","scope":4,"foreignInstall":false,"isSyncable":false},"formautofill@mozilla.org":{"id":"formautofill@mozilla.org","guid":"{76d755ad-d1b8-4317-a53e-a0e07bc82ada}","enabled":true,"installed":true,"modified":1772635467925,"type":"extension","scope":4,"foreignInstall":false,"isSyncable":false},"ipp-activator@mozilla.com":{"id":"ipp-activator@mozilla.com","guid":"{e8429a35-24eb-4ca2-aa45-fc46e9652f17}","enabled":true,"installed":true,"modified":1772635467925,"type":"extension","scope":4,"foreignInstall":false,"isSyncable":false},"newtab@mozilla.org":{"id":"newtab@mozilla.org","guid":"{686fe5a5-a3d2-48fc-8519-f9acf6bf3317}","enabled":true,"installed":true,"modified":1772635467925,"type":"extension","scope":4,"foreignInstall":false,"isSyncable":false},"pictureinpicture@mozilla.org":{"id":"pictureinpicture@mozilla.org","guid":"{f2d7f9f5-1b2f-4340-9297-ef0355afd211}","enabled":true,"installed":true,"modified":1772635467925,"type":"extension","scope":4,"foreignInstall":false,"isSyncable":false},"addons-search-detection@mozilla.com":{"id":"addons-search-detection@mozilla.com","guid":"{ef3eb746-9ec9-47be-9419-2aced7c05ebe}","enabled":true,"installed":true,"modified":1772635467926,"type":"extension","scope":4,"foreignInstall":false,"isSyncable":false},"firefox-compact-light@mozilla.org":{"id":"firefox-compact-light@mozilla.org","guid":"{33d7d991-b0a4-4275-9698-f70a51818ddb}","enabled":false,"installed":true,"modified":1772635467926,"type":"theme","scope":4,"foreignInstall":false,"isSyncable":false},"firefox-alpenglow@mozilla.org":{"id":"firefox-alpenglow@mozilla.org","guid":"{a77a6b78-85bc-4040-a8eb-ed048633ca4f}","enabled":false,"installed":true,"modified":1772635467926,"type":"theme","scope":4,"foreignInstall":false,"isSyncable":false},"webcompat@mozilla.org":{"id":"webcompat@mozilla.org","guid":"{76608445-9442-4a7a-8b3b-c3183d74ab72}","enabled":true,"installed":true,"modified":1772635467926,"type":"extension","scope":1,"foreignInstall":false,"isSyncable":false},"gmp-gmpopenh264":{"id":"gmp-gmpopenh264","enabled":true,"installed":true,"modified":1772635467926,"type":"plugin","scope":4,"foreignInstall":false},"gmp-widevinecdm":{"id":"gmp-widevinecdm","enabled":true,"installed":true,"modified":1772635467926,"type":"plugin","scope":4,"foreignInstall":false},"wappalyzer@crunchlabz.com":{"id":"wappalyzer@crunchlabz.com","guid":"{31627af2-d596-4fad-968f-8675c2c717ca}","enabled":true,"installed":true,"modified":1772635479200,"type":"extension","scope":1,"foreignInstall":false,"isSyncable":true},"BraveSearchExtension@io.Uvera":{"id":"BraveSearchExtension@io.Uvera","guid":"{34b806b1-a749-46db-8234-73d7b40362a4}","enabled":true,"installed":true,"modified":1772635479984,"type":"extension","scope":1,"foreignInstall":false,"isSyncable":true},"{6AC85730-7D0F-4de0-B3FA-21142DD85326}":{"id":"{6AC85730-7D0F-4de0-B3FA-21142DD85326}","guid":"{69d4f8f6-9939-41d3-8c31-88f6e3462fdb}","enabled":true,"installed":true,"modified":1772635480763,"type":"extension","scope":1,"foreignInstall":false,"isSyncable":true},"SaveImageAsType@d7om.dev":{"id":"SaveImageAsType@d7om.dev","guid":"{9bffad37-8bf7-4e37-9c66-ce08c2c565d5}","enabled":true,"installed":true,"modified":1772635481454,"type":"extension","scope":1,"foreignInstall":false,"isSyncable":true},"newspass@newspass.com":{"id":"newspass@newspass.com","guid":"{d80649c1-07a1-45df-9bfe-757b2942d3ac}","enabled":true,"installed":true,"modified":1772635482256,"type":"extension","scope":1,"foreignInstall":false,"isSyncable":true},"uBlock0@raymondhill.net":{"id":"uBlock0@raymondhill.net","guid":"{dd422680-5b6a-4c89-9b47-4523706daee6}","enabled":true,"installed":true,"modified":1772635486626,"type":"extension","scope":1,"foreignInstall":false,"isSyncable":true},"addon@darkreader.org":{"id":"addon@darkreader.org","guid":"{f42d050b-d263-4b18-8ffb-52c11adba3f6}","enabled":true,"installed":true,"modified":1772635487430,"type":"extension","scope":1,"foreignInstall":false,"isSyncable":true}},"changes":[[1772635462769,1,"firefox-compact-dark@mozilla.org"],[1772635462792,1,"default-theme@mozilla.org"],[1772635467925,1,"data-leak-blocker@mozilla.com"],[1772635467925,1,"formautofill@mozilla.org"],[1772635467925,1,"ipp-activator@mozilla.com"],[1772635467925,1,"newtab@mozilla.org"],[1772635467925,1,"pictureinpicture@mozilla.org"],[1772635467926,1,"addons-search-detection@mozilla.com"],[1772635467926,1,"firefox-compact-light@mozilla.org"],[1772635467926,1,"firefox-alpenglow@mozilla.org"],[1772635467926,1,"webcompat@mozilla.org"],[1772635467926,1,"gmp-gmpopenh264"],[1772635467926,1,"gmp-widevinecdm"],[1772635479200,1,"wappalyzer@crunchlabz.com"],[1772635479984,1,"BraveSearchExtension@io.Uvera"],[1772635480763,1,"{6AC85730-7D0F-4de0-B3FA-21142DD85326}"],[1772635481454,1,"SaveImageAsType@d7om.dev"],[1772635482256,1,"newspass@newspass.com"],[1772635486626,1,"uBlock0@raymondhill.net"],[1772635487430,1,"addon@darkreader.org"]]}